find_dependencies/__init__.py
find_dependencies/dependency_finder.py
find_dependencies/plugin.py
pytest_find_dependencies-0.6.0.dist-info/licenses/LICENSE
pytest_find_dependencies-0.6.0.dist-info/METADATA
pytest_find_dependencies-0.6.0.dist-info/WHEEL
pytest_find_dependencies-0.6.0.dist-info/entry_points.txt
pytest_find_dependencies-0.6.0.dist-info/top_level.txt
pytest_find_dependencies-0.6.0.dist-info/RECORD
