Metadata-Version: 2.4
Name: pytest-find-dependencies
Version: 0.6.0
Summary: A pytest plugin to find dependencies between tests
Author-email: mrbean-bremen <hansemrbean@googlemail.com>
License-Expression: MIT
Project-URL: homepage, https://github.com/mrbean-bremen/pytest-find-dependencies
Project-URL: repository, https://github.com/mrbean-bremen/pytest-find-dependencies
Project-URL: changelog, https://github.com/mrbean-bremen/pytest-find-dependencies/blob/main/CHANGELOG.rst
Project-URL: issues, https://github.com/mrbean-bremen/pytest-find-dependencies/issues
Keywords: testing,pytest,dependencies
Classifier: Intended Audience :: Developers
Classifier: Development Status :: 5 - Production/Stable
Classifier: Environment :: Console
Classifier: Programming Language :: Python
Classifier: Programming Language :: Python :: 3.9
Classifier: Programming Language :: Python :: 3.10
Classifier: Programming Language :: Python :: 3.11
Classifier: Programming Language :: Python :: 3.12
Classifier: Programming Language :: Python :: 3.13
Classifier: Operating System :: POSIX :: Linux
Classifier: Operating System :: MacOS
Classifier: Operating System :: Microsoft :: Windows
Classifier: Topic :: Software Development :: Testing
Classifier: Topic :: Software Development :: Quality Assurance
Classifier: Topic :: Utilities
Requires-Python: >=3.9
License-File: LICENSE
Requires-Dist: pytest>=6.2.4
Provides-Extra: dev
Requires-Dist: pytest-randomly; extra == "dev"
Requires-Dist: pytest-xdist; extra == "dev"
Requires-Dist: pre-commit>=4.1.4; extra == "dev"
Dynamic: license-file
